SKD/__init__.py
SKD/core.py
SKD/get_official_data.py
soul_knight_data_processing-0.0.9.dist-info/METADATA
soul_knight_data_processing-0.0.9.dist-info/WHEEL
soul_knight_data_processing-0.0.9.dist-info/licenses/LICENSE
soul_knight_data_processing-0.0.9.dist-info/RECORD
