Metadata-Version: 2.3
Name: soul_knight_data_processing
Version: 0.0.9
Summary: A package for encode or decode soul_knight data files.
Project-URL: Homepage, https://github.com/Suto-Commune/soul_knight/
Author-email: Roren Natsumi <RorenNatsumi@outlook.com>
License:                     GNU GENERAL PUBLIC LICENSE
License-File: LICENSE
Requires-Dist: pycryptodome
Requires-Dist: requests
Requires-Dist: wget
